keylime/__init__.py
keylime/agentstates.py
keylime/api_version.py
keylime/backport_dataclasses.py
keylime/ca_impl_openssl.py
keylime/ca_util.py
keylime/cert_utils.py
keylime/cloud_verifier_common.py
keylime/cloud_verifier_tornado.py
keylime/cmd_exec.py
keylime/config.py
keylime/crypto.py
keylime/failure.py
keylime/fs_util.py
keylime/ip_util.py
keylime/json.py
keylime/keylime_logging.py
keylime/registrar_client.py
keylime/requests_client.py
keylime/revocation_notifier.py
keylime/signing.py
keylime/tenant.py
keylime/tornado_requests.py
keylime/tpm_ek_ca.py
keylime/types.py
keylime/web_util.py
keylime/cli/__init__.py
keylime/cli/options.py
keylime/cli/policies.py
keylime/cmd/__init__.py
keylime/cmd/attest.py
keylime/cmd/ca.py
keylime/cmd/convert_config.py
keylime/cmd/convert_runtime_policy.py
keylime/cmd/create_policy.py
keylime/cmd/keylime_policy.py
keylime/cmd/registrar.py
keylime/cmd/sign_runtime_policy.py
keylime/cmd/tenant.py
keylime/cmd/user_data_encrypt.py
keylime/cmd/verifier.py
keylime/common/__init__.py
keylime/common/algorithms.py
keylime/common/exception.py
keylime/common/migrations.py
keylime/common/retry.py
keylime/common/states.py
keylime/common/validators.py
keylime/common/version.py
keylime/da/__init__.py
keylime/da/attest.py
keylime/da/record.py
keylime/da/examples/__init__.py
keylime/da/examples/file.py
keylime/da/examples/redis.py
keylime/da/examples/rekor.py
keylime/da/examples/sqldb.py
keylime/da/examples/tsa_rfc3161.py
keylime/db/__init__.py
keylime/db/keylime_db.py
keylime/db/registrar_db.py
keylime/db/verifier_db.py
keylime/dsse/__init__.py
keylime/dsse/dsse.py
keylime/dsse/ecdsa.py
keylime/dsse/x509.py
keylime/ima/__init__.py
keylime/ima/ast.py
keylime/ima/dm_grammar.py
keylime/ima/file_signatures.py
keylime/ima/ima.py
keylime/ima/ima_dm.py
keylime/ima/types.py
keylime/mba/__init__.py
keylime/mba/mba.py
keylime/mba/elchecking/__init__.py
keylime/mba/elchecking/__main__.py
keylime/mba/elchecking/elchecker.py
keylime/mba/elchecking/example.py
keylime-7.12.0.dist-info/LICENSE
keylime-7.12.0.dist-info/METADATA
keylime-7.12.0.dist-info/WHEEL
keylime-7.12.0.dist-info/entry_points.txt
keylime-7.12.0.dist-info/top_level.txt
keylime-7.12.0.dist-info/RECORD
