Metadata-Version: 2.2
Name: keylime
Version: 7.12.0
Summary: TPM-based key bootstrapping and system integrity measurement system for cloud
Home-page: https://keylime.dev
Author: Keylime Community
Author-email: keylime@groups.io
License: Apache-2.0
Project-URL: Source, https://github.com/keylime/keylime
Project-URL: Documentation, https://keylime.readthedocs.io/en/latest/
Keywords: iot,security,cloud,edge,tpm,ima,attestation,virtualization
Classifier: Environment :: Console
Classifier: Intended Audience :: Developers
Classifier: Intended Audience :: Information Technology
Classifier: Intended Audience :: System Administrators
Classifier: License :: OSI Approved :: Apache Software License
Classifier: Operating System :: POSIX :: Linux
Classifier: Programming Language :: Python
Classifier: Programming Language :: Python :: Implementation :: CPython
Classifier: Programming Language :: Python :: 3 :: Only
Classifier: Programming Language :: Python :: 3
Classifier: Programming Language :: Python :: 3.6
Classifier: Programming Language :: Python :: 3.7
Classifier: Programming Language :: Python :: 3.8
Classifier: Programming Language :: Python :: 3.9
Classifier: Programming Language :: Python :: 3.10
Classifier: Topic :: System :: Hardware
Requires-Python: >=3.6
License-File: LICENSE
